{
    "1": {
        "id": 7,
        "planet": "Atlantis",
        "days": [
            "4"
        ],
        "quality": "Standard",
        "breakfast": "Yes",
        "relax": "Yes",
        "nbpeople": 1,
        "insurance": "No",
        "payment_transaction": 1600,
        "selectedDate": "4",
        "payed": false
    },
    "2": {
        "id": 7,
        "planet": "Atlantis",
        "days": [
            "4"
        ],
        "quality": "Standard",
        "breakfast": "Yes",
        "relax": "Yes",
        "nbpeople": 1,
        "insurance": "Yes",
        "payment_transaction": "gXsXyORDMzXfM",
        "selectedDate": "5",
        "payed": true,
        "payment_amount": "1630"
    }
}
